attogradDB/__init__.py
attogradDB/attodb.py
attogradDB/embedding.py
attogradDB/indexing.py
attogradDB/io.py
attogradDB/tokenizer.py
attogradDB/utils.py
attogradDB-0.4.dist-info/LICENSE
attogradDB-0.4.dist-info/METADATA
attogradDB-0.4.dist-info/WHEEL
attogradDB-0.4.dist-info/top_level.txt
attogradDB-0.4.dist-info/RECORD
