Metadata-Version: 2.1
Name: attogradDB
Version: 0.4
Summary: A simple vector database for fast similarity search
Home-page: https://github.com/gouthamk16/attogradDB
Author: Goutham Krishnan
License: MIT
Classifier: Programming Language :: Python :: 3.6
Classifier: License :: OSI Approved :: MIT License
Classifier: Operating System :: OS Independent
Requires-Python: >=3.11
License-File: LICENSE
Requires-Dist: numpy
Requires-Dist: scipy
Requires-Dist: tiktoken
Requires-Dist: transformers
Requires-Dist: accelerate
Requires-Dist: huggingface-hub
Requires-Dist: PyPDF2
Requires-Dist: graphing
Requires-Dist: hnswlib
Provides-Extra: dev
Requires-Dist: pytest; extra == "dev"
Requires-Dist: twine; extra == "dev"
